agentvectordb/__init__.py
agentvectordb/agent_memory.py
agentvectordb/async_agent_memory.py
agentvectordb/async_collection.py
agentvectordb/async_store.py
agentvectordb/collection.py
agentvectordb/embeddings.py
agentvectordb/exceptions.py
agentvectordb/schemas.py
agentvectordb/store.py
agentvectordb/utils.py
agentvectordb-0.0.3.dist-info/licenses/LICENCE
agentvectordb-0.0.3.dist-info/METADATA
agentvectordb-0.0.3.dist-info/WHEEL
agentvectordb-0.0.3.dist-info/top_level.txt
agentvectordb-0.0.3.dist-info/RECORD
