Metadata-Version: 2.4
Name: agentvectordb
Version: 0.0.3
Summary: AgentVectorDB (AVDB): The Cognitive Core for Your AI Agents. A lightweight, embeddable vector database for Agentic AI systems, built on LanceDB.
Author-email: Shashi Jagtap <shashi@super-agentic.ai>, Shashikant Jagtap <shashikant.jagtap@icloud.com>
Project-URL: Homepage, https://github.com/superagenticai/agentvectordb
Project-URL: Repository, https://github.com/superagenticai/agentvectordb
Classifier: Development Status :: 3 - Alpha
Classifier: Intended Audience :: Developers
Classifier: Intended Audience :: Science/Research
Classifier: Programming Language :: Python :: 3
Classifier: Programming Language :: Python :: 3.8
Classifier: Programming Language :: Python :: 3.9
Classifier: Programming Language :: Python :: 3.10
Classifier: Programming Language :: Python :: 3.11
Classifier: Programming Language :: Python :: 3.12
Classifier: Topic :: Scientific/Engineering :: Artificial Intelligence
Classifier: Topic :: Database
Classifier: Operating System :: OS Independent
Requires-Python: >=3.8
License-File: LICENCE
Requires-Dist: lancedb
Requires-Dist: pandas
Requires-Dist: pydantic>=2.0
Requires-Dist: numpy
Requires-Dist: pyarrow>=12.0.1
Requires-Dist: tantivy
Provides-Extra: dev
Requires-Dist: pytest>=7.0.0; extra == "dev"
Requires-Dist: pytest-cov; extra == "dev"
Requires-Dist: pytest-asyncio; extra == "dev"
Requires-Dist: pre-commit; extra == "dev"
Dynamic: license-file
